bodhi/messages/__init__.py
bodhi/messages/schemas/__init__.py
bodhi/messages/schemas/base.py
bodhi/messages/schemas/buildroot_override.py
bodhi/messages/schemas/compose.py
bodhi/messages/schemas/errata.py
bodhi/messages/schemas/update.py
bodhi/messages/utils.py
bodhi_messages-25.11.3.dist-info/METADATA
bodhi_messages-25.11.3.dist-info/WHEEL
bodhi_messages-25.11.3.dist-info/entry_points.txt
bodhi_messages-25.11.3.dist-info/licenses/COPYING
bodhi_messages-25.11.3.dist-info/RECORD
