Metadata-Version: 2.4
Name: bodhi-messages
Version: 25.11.3
Summary: JSON schema for messages sent by Bodhi
License: GPL-2.0-or-later
License-File: COPYING
Keywords: fedora,fedora-messaging
Author: Fedora Infrastructure Team
Maintainer: Fedora Infrastructure Team
Maintainer-email: infrastructure@lists.fedoraproject.org
Requires-Python: >=3.9,<4
Classifier: Development Status :: 5 - Production/Stable
Classifier: Intended Audience :: Developers
Classifier: Intended Audience :: System Administrators
Classifier: License :: OSI Approved :: GNU General Public License v2 or later (GPLv2+)
Classifier: Operating System :: POSIX :: Linux
Classifier: Programming Language :: Python :: 3
Classifier: Programming Language :: Python :: 3.9
Classifier: Programming Language :: Python :: 3.10
Classifier: Programming Language :: Python :: 3.11
Classifier: Programming Language :: Python :: 3.12
Classifier: Programming Language :: Python :: 3.13
Classifier: Programming Language :: Python :: 3.14
Classifier: Topic :: System :: Software Distribution
Requires-Dist: fedora-messaging (>=3.0.0)
Project-URL: Homepage, https://bodhi.fedoraproject.org
Project-URL: Repository, https://github.com/fedora-infra/bodhi
